pdmp_jax/__init__.py
pdmp_jax/brent.py
pdmp_jax/namedtuples.py
pdmp_jax/samplers/Boomerang.py
pdmp_jax/samplers/BouncyParticle.py
pdmp_jax/samplers/ForwardEventChain.py
pdmp_jax/samplers/SpeedupZigZag.py
pdmp_jax/samplers/ZigZag.py
pdmp_jax/samplers/__init__.py
pdmp_jax/samplers/pdmp.py
pdmp_jax/sampling_loop.py
pdmp_jax/upper_bound.py
pdmp_jax-0.1.1.dist-info/LICENSE
pdmp_jax-0.1.1.dist-info/METADATA
pdmp_jax-0.1.1.dist-info/WHEEL
pdmp_jax-0.1.1.dist-info/RECORD
