Metadata-Version: 2.1
Name: pdmp-jax
Version: 0.1.1
Summary: A general PDMP sampler in JAX
Home-page: https://github.com/charlyandral/pdmp_jax
License: MIT
Author: Charly Andral
Author-email: andral@ceremade.dauphine.fr
Requires-Python: >=3.10,<4.0
Classifier: License :: OSI Approved :: MIT License
Classifier: Programming Language :: Python :: 3
Classifier: Programming Language :: Python :: 3.10
Classifier: Programming Language :: Python :: 3.11
Classifier: Programming Language :: Python :: 3.12
Requires-Dist: jax (>=0.4.31,<0.5.0)
Requires-Dist: jax-tqdm (>=0.2.2,<0.3.0)
Requires-Dist: jaxlib (>=0.4.31,<0.5.0)
Requires-Dist: jaxtyping (>=0.2.33,<0.3.0)
Requires-Dist: matplotlib (>=3.9.1,<4.0.0)
Requires-Dist: seaborn (>=0.13.2,<0.14.0)
Project-URL: Repository, https://github.com/charlyandral/pdmp_jax
